async_adbc/__init__.py
async_adbc/adbclient.py
async_adbc/device.py
async_adbc/exceptions.py
async_adbc/plugin.py
async_adbc/plugins/__init__.py
async_adbc/plugins/am.py
async_adbc/plugins/battery.py
async_adbc/plugins/cpu.py
async_adbc/plugins/forward.py
async_adbc/plugins/fps.py
async_adbc/plugins/gpu.py
async_adbc/plugins/input.py
async_adbc/plugins/logcat.py
async_adbc/plugins/mem.py
async_adbc/plugins/minicap.py
async_adbc/plugins/pm.py
async_adbc/plugins/prop.py
async_adbc/plugins/temp.py
async_adbc/plugins/traffic.py
async_adbc/plugins/utils.py
async_adbc/plugins/wm.py
async_adbc/protocol.py
async_adbc/service/__init__.py
async_adbc/service/host.py
async_adbc/service/local.py
async_adbc/vendor/__init__.py
async_adbc/vendor/minicap/arm64-v8a/minicap
async_adbc/vendor/minicap/arm64-v8a/minicap-nopie
async_adbc/vendor/minicap/arm64-v8a/minicap.so
async_adbc/vendor/minicap/arm64-v8a/minitouch
async_adbc/vendor/minicap/arm64-v8a/minitouch-nopie
async_adbc/vendor/minicap/armeabi/minitouch
async_adbc/vendor/minicap/armeabi/minitouch-nopie
async_adbc/vendor/minicap/armeabi-v7a/minicap
async_adbc/vendor/minicap/armeabi-v7a/minicap-nopie
async_adbc/vendor/minicap/armeabi-v7a/minicap.so
async_adbc/vendor/minicap/armeabi-v7a/minitouch
async_adbc/vendor/minicap/armeabi-v7a/minitouch-nopie
async_adbc/vendor/minicap/minicap-shared/aosp/libs/android-10/armeabi-v7a/minicap.so
async_adbc/vendor/minicap/minicap-shared/aosp/libs/android-14/armeabi-v7a/minicap.so
async_adbc/vendor/minicap/minicap-shared/aosp/libs/android-14/x86/minicap.so
async_adbc/vendor/minicap/minicap-shared/aosp/libs/android-15/armeabi-v7a/minicap.so
async_adbc/vendor/minicap/minicap-shared/aosp/libs/android-15/x86/minicap.so
async_adbc/vendor/minicap/minicap-shared/aosp/libs/android-16/armeabi-v7a/minicap.so
async_adbc/vendor/minicap/minicap-shared/aosp/libs/android-16/x86/minicap.so
async_adbc/vendor/minicap/minicap-shared/aosp/libs/android-17/armeabi-v7a/minicap.so
async_adbc-1.1.2.dist-info/LICENSE
async_adbc-1.1.2.dist-info/METADATA
async_adbc-1.1.2.dist-info/WHEEL
async_adbc-1.1.2.dist-info/RECORD
