Metadata-Version: 2.3
Name: async-adbc
Version: 1.1.2
Summary: 
Author: kaluluosi
Author-email: kaluluosi@gmail.com
Requires-Python: >=3.8,<4.0
Classifier: Programming Language :: Python :: 3
Classifier: Programming Language :: Python :: 3.8
Classifier: Programming Language :: Python :: 3.9
Classifier: Programming Language :: Python :: 3.10
Classifier: Programming Language :: Python :: 3.11
Classifier: Programming Language :: Python :: 3.12
Classifier: Programming Language :: Python :: 3.13
Requires-Dist: async-lru (>=2.0.4,<3.0.0)
Requires-Dist: pydantic (>=2.5.1,<3.0.0)
Project-URL: Repository, https://github.com/kaluluosi/async-adbc
